tcrdiscord/__init__.py
tcrdiscord/__main__.py
tcrdiscord/version.py
tcrdiscord/src/tcrd_alias.py
tcrdiscord/src/tcrd_cached_fetch.py
tcrdiscord/src/tcrd_commands.py
tcrdiscord/src/tcrd_constants.py
tcrdiscord/src/tcrd_dpy.py
tcrdiscord/src/tcrd_embeds.py
tcrdiscord/src/tcrd_limits.py
tcrdiscord/src/tcrd_markdown.py
tcrdiscord/src/tcrd_permissions.py
tcrdiscord/src/tcrd_shorts.py
tcrdiscord/src/tcrd_snowflake.py
tcrdiscord/src/tcrd_string.py
tcrdiscord/src/tcrd_types.py
tcrdiscord-0.0.12.dist-info/LICENSE
tcrdiscord-0.0.12.dist-info/METADATA
tcrdiscord-0.0.12.dist-info/WHEEL
tcrdiscord-0.0.12.dist-info/top_level.txt
tcrdiscord-0.0.12.dist-info/RECORD
